fastapi_agmin/__init__.py
fastapi_agmin/agmin.py
fastapi_agmin/static/index.html
fastapi_agmin/static/vite.svg
fastapi_agmin/static/assets/HomeView-DKlFP5ja.css
fastapi_agmin/static/assets/HomeView-Dcr4wPqG.js
fastapi_agmin/static/assets/ModelAndRelated-B2MFACuO.css
fastapi_agmin/static/assets/ModelAndRelated-CeMh0wsu.js
fastapi_agmin/static/assets/duckdb-DnmI0-ym.js
fastapi_agmin/static/assets/index-CMWJxmaP.css
fastapi_agmin/static/assets/index-DkGslEEv.js
fastapi_agmin-0.4.0.dist-info/METADATA
fastapi_agmin-0.4.0.dist-info/WHEEL
fastapi_agmin-0.4.0.dist-info/top_level.txt
fastapi_agmin-0.4.0.dist-info/RECORD
