Metadata-Version: 2.4
Name: fastapi-agmin
Version: 0.4.0
Summary: A FastAPI package with CRUD endpoints and a Vue + AG Grid frontend for SQLAlchemy models.
Author-email: Pedro Viana <pedrovgp@gmail.com>
Project-URL: repository, https://github.com/pedrovgp/fastapi-agmin
Classifier: Programming Language :: Python :: 3
Classifier: Framework :: FastAPI
Classifier: License :: OSI Approved :: MIT License
Classifier: Operating System :: OS Independent
Requires-Python: >=3.11
Requires-Dist: fastapi>=0.68.0
Requires-Dist: uvicorn>=0.28.0
Requires-Dist: sqlalchemy>=1.4.0
Requires-Dist: pydantic>=2.0.0
Requires-Dist: PyYAML>=6.0.0
Provides-Extra: dev
Requires-Dist: pytest-playwright>=0.7.0; extra == "dev"
Requires-Dist: ruff>=0.11.8; extra == "dev"
Requires-Dist: pytest>=8.3.5; extra == "dev"
Requires-Dist: httpx>=0.28.1; extra == "dev"
Requires-Dist: pytest-cov; extra == "dev"
Requires-Dist: pytest-asyncio; extra == "dev"
Requires-Dist: pre-commit>=4.2.0; extra == "dev"
